MANIFEST.in
runtests.py
setup.py
Qlik_Script_Tools.egg-info/PKG-INFO
Qlik_Script_Tools.egg-info/SOURCES.txt
Qlik_Script_Tools.egg-info/dependency_links.txt
Qlik_Script_Tools.egg-info/entry_points.txt
Qlik_Script_Tools.egg-info/top_level.txt
blocks/Default_Call_Meta.xml
blocks/Default_Init_Meta.xml
blocks/Default_Start.xml
blocks/Default_Sub_Meta.xml
blocks/Sub_Metadata.xml
blocks/Subbify_Main.xml
blocks/Subbify_SmartCall_Init.xml
blocks/Subbify_SmartCall_Run.xml
blocks/Subbify_Sub_Metadata.xml
blocks/Subbify_Template_End.xml
blocks/Subbify_Template_Mid.xml
blocks/Subbify_Template_Start.xml
docs/examples.rst
docs/index.rst
docs/modules.rst
qvstools/__init__.py
qvstools/blocks.py
qvstools/log.py
qvstools/prj.py
qvstools/qvd.py
qvstools/regex_store.py
qvstools/subbify.py
qvstools/text.py
qvstools/subbify_source/Subbified.qvw
qvstools/subbify_source/Subbify_Main.xml
qvstools/subbify_source/Subbify_SmartCall_Init.xml
qvstools/subbify_source/Subbify_SmartCall_Run.xml
qvstools/subbify_source/Subbify_Sub_Metadata.xml
qvstools/subbify_source/Subbify_Template_End.xml
qvstools/subbify_source/Subbify_Template_Mid.xml
qvstools/subbify_source/Subbify_Template_Start.xml
qvstools/subbify_source/Subbified-prj/AllProperties.xml
qvstools/subbify_source/Subbified-prj/CH01_238332217.xml
qvstools/subbify_source/Subbified-prj/CH02_438168158.xml
qvstools/subbify_source/Subbified-prj/DocBinary.dat
qvstools/subbify_source/Subbified-prj/DocInternals.xml
qvstools/subbify_source/Subbified-prj/DocProperties.xml
qvstools/subbify_source/Subbified-prj/IB01_312372977.xml
qvstools/subbify_source/Subbified-prj/LB01_694069076.xml
qvstools/subbify_source/Subbified-prj/LoadScript.txt
qvstools/subbify_source/Subbified-prj/Log.txt
qvstools/subbify_source/Subbified-prj/Module.txt
qvstools/subbify_source/Subbified-prj/QlikViewProject.xml
qvstools/subbify_source/Subbified-prj/SH01.xml
qvstools/subbify_source/Subbified-prj/TB01_545340463.xml
qvstools/subbify_source/Subbified-prj/TX01_925115006.xml
qvstools/subbify_source/Subbified-prj/TX02_510147791.xml
qvstools/subbify_source/Subbified-prj/TX03_286566380.xml
qvstools/subbify_source/Subbified-prj/TX04_449838177.xml
